nlmpy/__init__.py
nlmpy/nlmpy.py
nlmpy/nlmpyNetwork.py
nlmpy-1.2.0.dist-info/METADATA
nlmpy-1.2.0.dist-info/WHEEL
nlmpy-1.2.0.dist-info/licenses/LICENSE.txt
nlmpy-1.2.0.dist-info/RECORD
