Metadata-Version: 2.1
Name: nlmpy
Version: 1.2.0
Summary: A Python package to create neutral landscape models
Project-URL: Homepage, https://github.com/tretherington/nlmpy
Author: E. Penelope Holland, David O'Sullivan, Pierre Vigier
Author-email: "Thomas R. Etherington" <etheringtont@landcareresearch.co.nz>
License-File: LICENSE.txt
Classifier: License :: OSI Approved :: MIT License
Classifier: Operating System :: OS Independent
Classifier: Programming Language :: Python :: 3
Requires-Python: >=3
